mitesh/__init__.py
mitesh/mitesh.py
mitesh/version.py
mitesh-0.0.0.dist-info/LICENSE
mitesh-0.0.0.dist-info/METADATA
mitesh-0.0.0.dist-info/WHEEL
mitesh-0.0.0.dist-info/top_level.txt
mitesh-0.0.0.dist-info/RECORD
