Metadata-Version: 2.1
Name: mitesh
Version: 0.0.0
Summary: Modestly Integrated To Every SHell
Home-page: https://github.com/miteshbsjat/mitesh
Author: Mitesh Singh Jat
Author-email: mitesh.singh.jat@gmail.com
License: Apache License 2.0
Download-URL: https://github.com/miteshbsjat/mitesh/archive/refs/tags/0.0.0.tar.gz
Project-URL: Bug Tracker, https://github.com/miteshbsjat/mitesh/issues
Keywords: pypi,mitesh,shell
Platform: UNKNOWN
Classifier: Development Status :: 3 - Alpha
Classifier: Intended Audience :: Developers
Classifier: Intended Audience :: System Administrators
Classifier: Topic :: Software Development :: Documentation
Classifier: Topic :: Software Development :: Libraries
Classifier: Topic :: Software Development :: Libraries :: Python Modules
Classifier: Topic :: System
Classifier: Topic :: System :: Operating System
Classifier: Topic :: System :: Shells
Classifier: Topic :: System :: System Shells
Classifier: Topic :: System :: Systems Administration
Classifier: Topic :: Text Processing
Classifier: Topic :: Utilities
Classifier: License :: OSI Approved :: Apache Software License
Classifier: Operating System :: POSIX
Classifier: Operating System :: MacOS
Classifier: Operating System :: Unix
Classifier: Programming Language :: Python :: 3
Classifier: Programming Language :: Python :: 3.6
Classifier: Programming Language :: Python :: 3.7
Classifier: Programming Language :: Python :: 3.8
Classifier: Programming Language :: Python :: 3.9
